[{"left_prior": 0, "attrs": [], "is_leaf": false, "last_sibling": true, "right_prior": 0, "right_sibling": 0, "parent": 0, "left_sibling": 0, "num_children": 158, "node_number": 0, "label": "FileAST"}, {"left_prior": 0, "attrs": [], "is_leaf": false, "last_sibling": true, "right_prior": 2, "right_sibling": 0, "parent": 0, "left_sibling": 0, "num_children": 2, "node_number": 1, "label": "FuncDef"}, {"left_prior": 1, "attrs": [], "is_leaf": false, "last_sibling": true, "right_prior": 3, "right_sibling": 0, "parent": 1, "left_sibling": 0, "num_children": 8, "node_number": 2, "label": "Compound"}, {"left_prior": 2, "attrs": [], "is_leaf": false, "last_sibling": false, "right_prior": 4, "right_sibling": 14, "parent": 2, "left_sibling": 0, "num_children": 2, "node_number": 3, "label": "If"}, {"left_prior": 3, "attrs": [["op", "!="]], "is_leaf": false, "last_sibling": false, "right_prior": 5, "right_sibling": 7, "parent": 3, "left_sibling": 0, "num_children": 2, "node_number": 4, "label": "BinaryOp"}, {"left_prior": 4, "attrs": [["name", "argc"]], "is_leaf": true, "last_sibling": false, "right_prior": 6, "right_sibling": 6, "parent": 4, "left_sibling": 0, "num_children": 0, "node_number": 5, "label": "ID"}, {"left_prior": 5, "attrs": [["type", "int"], ["value", "2"]], "is_leaf": true, "last_sibling": true, "right_prior": 7, "right_sibling": 0, "parent": 4, "left_sibling": 5, "num_children": 0, "node_number": 6, "label": "Constant"}, {"left_prior": 6, "attrs": [], "is_leaf": false, "last_sibling": true, "right_prior": 8, "right_sibling": 0, "parent": 3, "left_sibling": 4, "num_children": 2, "node_number": 7, "label": "Compound"}, {"left_prior": 7, "attrs": [], "is_leaf": false, "last_sibling": false, "right_prior": 9, "right_sibling": 12, "parent": 7, "left_sibling": 0, "num_children": 2, "node_number": 8, "label": "FuncCall"}, {"left_prior": 8, "attrs": [["name", "printf"]], "is_leaf": true, "last_sibling": false, "right_prior": 10, "right_sibling": 10, "parent": 8, "left_sibling": 0, "num_children": 0, "node_number": 9, "label": "ID"}, {"left_prior": 9, "attrs": [], "is_leaf": false, "last_sibling": true, "right_prior": 11, "right_sibling": 0, "parent": 8, "left_sibling": 9, "num_children": 1, "node_number": 10, "label": "ExprList"}, {"left_prior": 10, "attrs": [["type", "string"], ["value", "\"You have keyed in an invalid input, please key in an non-negative integer to proceed.\\n\""]], "is_leaf": true, "last_sibling": true, "right_prior": 12, "right_sibling": 0, "parent": 10, "left_sibling": 0, "num_children": 0, "node_number": 11, "label": "Constant"}, {"left_prior": 11, "attrs": [], "is_leaf": false, "last_sibling": true, "right_prior": 13, "right_sibling": 0, "parent": 7, "left_sibling": 8, "num_children": 1, "node_number": 12, "label": "Return"}, {"left_prior": 12, "attrs": [["type", "int"], ["value", "1"]], "is_leaf": true, "last_sibling": true, "right_prior": 14, "right_sibling": 0, "parent": 12, "left_sibling": 0, "num_children": 0, "node_number": 13, "label": "Constant"}, {"left_prior": 13, "attrs": [], "is_leaf": false, "last_sibling": false, "right_prior": 15, "right_sibling": 38, "parent": 2, "left_sibling": 3, "num_children": 4, "node_number": 14, "label": "For"}, {"left_prior": 14, "attrs": [["op", "<"]], "is_leaf": false, "last_sibling": false, "right_prior": 16, "right_sibling": 18, "parent": 14, "left_sibling": 0, "num_children": 2, "node_number": 15, "label": "BinaryOp"}, {"left_prior": 15, "attrs": [["name", "j"]], "is_leaf": true, "last_sibling": false, "right_prior": 17, "right_sibling": 17, "parent": 15, "left_sibling": 0, "num_children": 0, "node_number": 16, "label": "ID"}, {"left_prior": 16, "attrs": [["name", "n"]], "is_leaf": true, "last_sibling": true, "right_prior": 18, "right_sibling": 0, "parent": 15, "left_sibling": 16, "num_children": 0, "node_number": 17, "label": "ID"}, {"left_prior": 17, "attrs": [["op", "p++"]], "is_leaf": false, "last_sibling": false, "right_prior": 19, "right_sibling": 20, "parent": 14, "left_sibling": 15, "num_children": 1, "node_number": 18, "label": "UnaryOp"}, {"left_prior": 18, "attrs": [["name", "j"]], "is_leaf": true, "last_sibling": true, "right_prior": 20, "right_sibling": 0, "parent": 18, "left_sibling": 0, "num_children": 0, "node_number": 19, "label": "ID"}, {"left_prior": 19, "attrs": [], "is_leaf": false, "last_sibling": true, "right_prior": 21, "right_sibling": 0, "parent": 14, "left_sibling": 18, "num_children": 1, "node_number": 20, "label": "Compound"}, {"left_prior": 20, "attrs": [], "is_leaf": false, "last_sibling": true, "right_prior": 22, "right_sibling": 0, "parent": 20, "left_sibling": 0, "num_children": 2, "node_number": 21, "label": "If"}, {"left_prior": 21, "attrs": [["op", "!"]], "is_leaf": false, "last_sibling": false, "right_prior": 23, "right_sibling": 31, "parent": 21, "left_sibling": 0, "num_children": 1, "node_number": 22, "label": "UnaryOp"}, {"left_prior": 22, "attrs": [], "is_leaf": false, "last_sibling": true, "right_prior": 24, "right_sibling": 0, "parent": 22, "left_sibling": 0, "num_children": 2, "node_number": 23, "label": "FuncCall"}, {"left_prior": 23, "attrs": [["name", "isalpha"]], "is_leaf": true, "last_sibling": false, "right_prior": 25, "right_sibling": 25, "parent": 23, "left_sibling": 0, "num_children": 0, "node_number": 24, "label": "ID"}, {"left_prior": 24, "attrs": [], "is_leaf": false, "last_sibling": true, "right_prior": 26, "right_sibling": 0, "parent": 23, "left_sibling": 24, "num_children": 1, "node_number": 25, "label": "ExprList"}, {"left_prior": 25, "attrs": [], "is_leaf": false, "last_sibling": true, "right_prior": 27, "right_sibling": 0, "parent": 25, "left_sibling": 0, "num_children": 2, "node_number": 26, "label": "ArrayRef"}, {"left_prior": 26, "attrs": [], "is_leaf": false, "last_sibling": false, "right_prior": 28, "right_sibling": 30, "parent": 26, "left_sibling": 0, "num_children": 2, "node_number": 27, "label": "ArrayRef"}, {"left_prior": 27, "attrs": [["name", "argv"]], "is_leaf": true, "last_sibling": false, "right_prior": 29, "right_sibling": 29, "parent": 27, "left_sibling": 0, "num_children": 0, "node_number": 28, "label": "ID"}, {"left_prior": 28, "attrs": [["type", "int"], ["value", "1"]], "is_leaf": true, "last_sibling": true, "right_prior": 30, "right_sibling": 0, "parent": 27, "left_sibling": 28, "num_children": 0, "node_number": 29, "label": "Constant"}, {"left_prior": 29, "attrs": [["name", "j"]], "is_leaf": true, "last_sibling": true, "right_prior": 31, "right_sibling": 0, "parent": 26, "left_sibling": 27, "num_children": 0, "node_number": 30, "label": "ID"}, {"left_prior": 30, "attrs": [], "is_leaf": false, "last_sibling": true, "right_prior": 32, "right_sibling": 0, "parent": 21, "left_sibling": 22, "num_children": 2, "node_number": 31, "label": "Compound"}, {"left_prior": 31, "attrs": [], "is_leaf": false, "last_sibling": false, "right_prior": 33, "right_sibling": 36, "parent": 31, "left_sibling": 0, "num_children": 2, "node_number": 32, "label": "FuncCall"}, {"left_prior": 32, "attrs": [["name", "printf"]], "is_leaf": true, "last_sibling": false, "right_prior": 34, "right_sibling": 34, "parent": 32, "left_sibling": 0, "num_children": 0, "node_number": 33, "label": "ID"}, {"left_prior": 33, "attrs": [], "is_leaf": false, "last_sibling": true, "right_prior": 35, "right_sibling": 0, "parent": 32, "left_sibling": 33, "num_children": 1, "node_number": 34, "label": "ExprList"}, {"left_prior": 34, "attrs": [["type", "string"], ["value", "\"You have keyed in an invalid input, please key in an non-negative integer to proceed.\\n\""]], "is_leaf": true, "last_sibling": true, "right_prior": 36, "right_sibling": 0, "parent": 34, "left_sibling": 0, "num_children": 0, "node_number": 35, "label": "Constant"}, {"left_prior": 35, "attrs": [], "is_leaf": false, "last_sibling": true, "right_prior": 37, "right_sibling": 0, "parent": 31, "left_sibling": 32, "num_children": 1, "node_number": 36, "label": "Return"}, {"left_prior": 36, "attrs": [["type", "int"], ["value", "1"]], "is_leaf": true, "last_sibling": true, "right_prior": 38, "right_sibling": 0, "parent": 36, "left_sibling": 0, "num_children": 0, "node_number": 37, "label": "Constant"}, {"left_prior": 37, "attrs": [], "is_leaf": false, "last_sibling": false, "right_prior": 39, "right_sibling": 78, "parent": 2, "left_sibling": 14, "num_children": 4, "node_number": 38, "label": "For"}, {"left_prior": 38, "attrs": [["op", "<"]], "is_leaf": false, "last_sibling": false, "right_prior": 40, "right_sibling": 42, "parent": 38, "left_sibling": 0, "num_children": 2, "node_number": 39, "label": "BinaryOp"}, {"left_prior": 39, "attrs": [["name", "j"]], "is_leaf": true, "last_sibling": false, "right_prior": 41, "right_sibling": 41, "parent": 39, "left_sibling": 0, "num_children": 0, "node_number": 40, "label": "ID"}, {"left_prior": 40, "attrs": [["name", "n"]], "is_leaf": true, "last_sibling": true, "right_prior": 42, "right_sibling": 0, "parent": 39, "left_sibling": 40, "num_children": 0, "node_number": 41, "label": "ID"}, {"left_prior": 41, "attrs": [["op", "p++"]], "is_leaf": false, "last_sibling": false, "right_prior": 43, "right_sibling": 44, "parent": 38, "left_sibling": 39, "num_children": 1, "node_number": 42, "label": "UnaryOp"}, {"left_prior": 42, "attrs": [["name", "j"]], "is_leaf": true, "last_sibling": true, "right_prior": 44, "right_sibling": 0, "parent": 42, "left_sibling": 0, "num_children": 0, "node_number": 43, "label": "ID"}, {"left_prior": 43, "attrs": [], "is_leaf": false, "last_sibling": true, "right_prior": 45, "right_sibling": 0, "parent": 38, "left_sibling": 42, "num_children": 1, "node_number": 44, "label": "Compound"}, {"left_prior": 44, "attrs": [], "is_leaf": false, "last_sibling": true, "right_prior": 46, "right_sibling": 0, "parent": 44, "left_sibling": 0, "num_children": 3, "node_number": 45, "label": "If"}, {"left_prior": 45, "attrs": [], "is_leaf": false, "last_sibling": false, "right_prior": 47, "right_sibling": 54, "parent": 45, "left_sibling": 0, "num_children": 2, "node_number": 46, "label": "FuncCall"}, {"left_prior": 46, "attrs": [["name", "isupper"]], "is_leaf": true, "last_sibling": false, "right_prior": 48, "right_sibling": 48, "parent": 46, "left_sibling": 0, "num_children": 0, "node_number": 47, "label": "ID"}, {"left_prior": 47, "attrs": [], "is_leaf": false, "last_sibling": true, "right_prior": 49, "right_sibling": 0, "parent": 46, "left_sibling": 47, "num_children": 1, "node_number": 48, "label": "ExprList"}, {"left_prior": 48, "attrs": [], "is_leaf": false, "last_sibling": true, "right_prior": 50, "right_sibling": 0, "parent": 48, "left_sibling": 0, "num_children": 2, "node_number": 49, "label": "ArrayRef"}, {"left_prior": 49, "attrs": [], "is_leaf": false, "last_sibling": false, "right_prior": 51, "right_sibling": 53, "parent": 49, "left_sibling": 0, "num_children": 2, "node_number": 50, "label": "ArrayRef"}, {"left_prior": 50, "attrs": [["name", "argv"]], "is_leaf": true, "last_sibling": false, "right_prior": 52, "right_sibling": 52, "parent": 50, "left_sibling": 0, "num_children": 0, "node_number": 51, "label": "ID"}, {"left_prior": 51, "attrs": [["type", "int"], ["value", "1"]], "is_leaf": true, "last_sibling": true, "right_prior": 53, "right_sibling": 0, "parent": 50, "left_sibling": 51, "num_children": 0, "node_number": 52, "label": "Constant"}, {"left_prior": 52, "attrs": [["name", "j"]], "is_leaf": true, "last_sibling": true, "right_prior": 54, "right_sibling": 0, "parent": 49, "left_sibling": 50, "num_children": 0, "node_number": 53, "label": "ID"}, {"left_prior": 53, "attrs": [], "is_leaf": false, "last_sibling": false, "right_prior": 55, "right_sibling": 66, "parent": 45, "left_sibling": 46, "num_children": 1, "node_number": 54, "label": "Compound"}, {"left_prior": 54, "attrs": [["op", "="]], "is_leaf": false, "last_sibling": true, "right_prior": 56, "right_sibling": 0, "parent": 54, "left_sibling": 0, "num_children": 2, "node_number": 55, "label": "Assignment"}, {"left_prior": 55, "attrs": [], "is_leaf": false, "last_sibling": false, "right_prior": 57, "right_sibling": 59, "parent": 55, "left_sibling": 0, "num_children": 2, "node_number": 56, "label": "ArrayRef"}, {"left_prior": 56, "attrs": [["name", "key"]], "is_leaf": true, "last_sibling": false, "right_prior": 58, "right_sibling": 58, "parent": 56, "left_sibling": 0, "num_children": 0, "node_number": 57, "label": "ID"}, {"left_prior": 57, "attrs": [["name", "j"]], "is_leaf": true, "last_sibling": true, "right_prior": 59, "right_sibling": 0, "parent": 56, "left_sibling": 57, "num_children": 0, "node_number": 58, "label": "ID"}, {"left_prior": 58, "attrs": [["op", "-"]], "is_leaf": false, "last_sibling": true, "right_prior": 60, "right_sibling": 0, "parent": 55, "left_sibling": 56, "num_children": 2, "node_number": 59, "label": "BinaryOp"}, {"left_prior": 59, "attrs": [], "is_leaf": false, "last_sibling": false, "right_prior": 61, "right_sibling": 65, "parent": 59, "left_sibling": 0, "num_children": 2, "node_number": 60, "label": "ArrayRef"}, {"left_prior": 60, "attrs": [], "is_leaf": false, "last_sibling": false, "right_prior": 62, "right_sibling": 64, "parent": 60, "left_sibling": 0, "num_children": 2, "node_number": 61, "label": "ArrayRef"}, {"left_prior": 61, "attrs": [["name", "argv"]], "is_leaf": true, "last_sibling": false, "right_prior": 63, "right_sibling": 63, "parent": 61, "left_sibling": 0, "num_children": 0, "node_number": 62, "label": "ID"}, {"left_prior": 62, "attrs": [["type", "int"], ["value", "1"]], "is_leaf": true, "last_sibling": true, "right_prior": 64, "right_sibling": 0, "parent": 61, "left_sibling": 62, "num_children": 0, "node_number": 63, "label": "Constant"}, {"left_prior": 63, "attrs": [["name", "j"]], "is_leaf": true, "last_sibling": true, "right_prior": 65, "right_sibling": 0, "parent": 60, "left_sibling": 61, "num_children": 0, "node_number": 64, "label": "ID"}, {"left_prior": 64, "attrs": [["type", "int"], ["value", "65"]], "is_leaf": true, "last_sibling": true, "right_prior": 66, "right_sibling": 0, "parent": 59, "left_sibling": 60, "num_children": 0, "node_number": 65, "label": "Constant"}, {"left_prior": 65, "attrs": [], "is_leaf": false, "last_sibling": true, "right_prior": 67, "right_sibling": 0, "parent": 45, "left_sibling": 54, "num_children": 1, "node_number": 66, "label": "Compound"}, {"left_prior": 66, "attrs": [["op", "="]], "is_leaf": false, "last_sibling": true, "right_prior": 68, "right_sibling": 0, "parent": 66, "left_sibling": 0, "num_children": 2, "node_number": 67, "label": "Assignment"}, {"left_prior": 67, "attrs": [], "is_leaf": false, "last_sibling": false, "right_prior": 69, "right_sibling": 71, "parent": 67, "left_sibling": 0, "num_children": 2, "node_number": 68, "label": "ArrayRef"}, {"left_prior": 68, "attrs": [["name", "key"]], "is_leaf": true, "last_sibling": false, "right_prior": 70, "right_sibling": 70, "parent": 68, "left_sibling": 0, "num_children": 0, "node_number": 69, "label": "ID"}, {"left_prior": 69, "attrs": [["name", "j"]], "is_leaf": true, "last_sibling": true, "right_prior": 71, "right_sibling": 0, "parent": 68, "left_sibling": 69, "num_children": 0, "node_number": 70, "label": "ID"}, {"left_prior": 70, "attrs": [["op", "-"]], "is_leaf": false, "last_sibling": true, "right_prior": 72, "right_sibling": 0, "parent": 67, "left_sibling": 68, "num_children": 2, "node_number": 71, "label": "BinaryOp"}, {"left_prior": 71, "attrs": [], "is_leaf": false, "last_sibling": false, "right_prior": 73, "right_sibling": 77, "parent": 71, "left_sibling": 0, "num_children": 2, "node_number": 72, "label": "ArrayRef"}, {"left_prior": 72, "attrs": [], "is_leaf": false, "last_sibling": false, "right_prior": 74, "right_sibling": 76, "parent": 72, "left_sibling": 0, "num_children": 2, "node_number": 73, "label": "ArrayRef"}, {"left_prior": 73, "attrs": [["name", "argv"]], "is_leaf": true, "last_sibling": false, "right_prior": 75, "right_sibling": 75, "parent": 73, "left_sibling": 0, "num_children": 0, "node_number": 74, "label": "ID"}, {"left_prior": 74, "attrs": [["type", "int"], ["value", "1"]], "is_leaf": true, "last_sibling": true, "right_prior": 76, "right_sibling": 0, "parent": 73, "left_sibling": 74, "num_children": 0, "node_number": 75, "label": "Constant"}, {"left_prior": 75, "attrs": [["name", "j"]], "is_leaf": true, "last_sibling": true, "right_prior": 77, "right_sibling": 0, "parent": 72, "left_sibling": 73, "num_children": 0, "node_number": 76, "label": "ID"}, {"left_prior": 76, "attrs": [["type", "int"], ["value", "97"]], "is_leaf": true, "last_sibling": true, "right_prior": 78, "right_sibling": 0, "parent": 71, "left_sibling": 72, "num_children": 0, "node_number": 77, "label": "Constant"}, {"left_prior": 77, "attrs": [], "is_leaf": false, "last_sibling": false, "right_prior": 79, "right_sibling": 183, "parent": 2, "left_sibling": 38, "num_children": 2, "node_number": 78, "label": "If"}, {"left_prior": 78, "attrs": [["op", "!="]], "is_leaf": false, "last_sibling": false, "right_prior": 80, "right_sibling": 82, "parent": 78, "left_sibling": 0, "num_children": 2, "node_number": 79, "label": "BinaryOp"}, {"left_prior": 79, "attrs": [["name", "message"]], "is_leaf": true, "last_sibling": false, "right_prior": 81, "right_sibling": 81, "parent": 79, "left_sibling": 0, "num_children": 0, "node_number": 80, "label": "ID"}, {"left_prior": 80, "attrs": [["type", "int"], ["value", "0"]], "is_leaf": true, "last_sibling": true, "right_prior": 82, "right_sibling": 0, "parent": 79, "left_sibling": 80, "num_children": 0, "node_number": 81, "label": "Constant"}, {"left_prior": 81, "attrs": [], "is_leaf": false, "last_sibling": true, "right_prior": 83, "right_sibling": 0, "parent": 78, "left_sibling": 79, "num_children": 2, "node_number": 82, "label": "Compound"}, {"left_prior": 82, "attrs": [], "is_leaf": false, "last_sibling": false, "right_prior": 84, "right_sibling": 179, "parent": 82, "left_sibling": 0, "num_children": 4, "node_number": 83, "label": "For"}, {"left_prior": 83, "attrs": [["op", "<"]], "is_leaf": false, "last_sibling": false, "right_prior": 85, "right_sibling": 87, "parent": 83, "left_sibling": 0, "num_children": 2, "node_number": 84, "label": "BinaryOp"}, {"left_prior": 84, "attrs": [["name", "i"]], "is_leaf": true, "last_sibling": false, "right_prior": 86, "right_sibling": 86, "parent": 84, "left_sibling": 0, "num_children": 0, "node_number": 85, "label": "ID"}, {"left_prior": 85, "attrs": [["name", "m"]], "is_leaf": true, "last_sibling": true, "right_prior": 87, "right_sibling": 0, "parent": 84, "left_sibling": 85, "num_children": 0, "node_number": 86, "label": "ID"}, {"left_prior": 86, "attrs": [["op", "p++"]], "is_leaf": false, "last_sibling": false, "right_prior": 88, "right_sibling": 89, "parent": 83, "left_sibling": 84, "num_children": 1, "node_number": 87, "label": "UnaryOp"}, {"left_prior": 87, "attrs": [["name", "i"]], "is_leaf": true, "last_sibling": true, "right_prior": 89, "right_sibling": 0, "parent": 87, "left_sibling": 0, "num_children": 0, "node_number": 88, "label": "ID"}, {"left_prior": 88, "attrs": [], "is_leaf": false, "last_sibling": true, "right_prior": 90, "right_sibling": 0, "parent": 83, "left_sibling": 87, "num_children": 1, "node_number": 89, "label": "Compound"}, {"left_prior": 89, "attrs": [], "is_leaf": false, "last_sibling": true, "right_prior": 91, "right_sibling": 0, "parent": 89, "left_sibling": 0, "num_children": 3, "node_number": 90, "label": "If"}, {"left_prior": 90, "attrs": [], "is_leaf": false, "last_sibling": false, "right_prior": 92, "right_sibling": 97, "parent": 90, "left_sibling": 0, "num_children": 2, "node_number": 91, "label": "FuncCall"}, {"left_prior": 91, "attrs": [["name", "isalpha"]], "is_leaf": true, "last_sibling": false, "right_prior": 93, "right_sibling": 93, "parent": 91, "left_sibling": 0, "num_children": 0, "node_number": 92, "label": "ID"}, {"left_prior": 92, "attrs": [], "is_leaf": false, "last_sibling": true, "right_prior": 94, "right_sibling": 0, "parent": 91, "left_sibling": 92, "num_children": 1, "node_number": 93, "label": "ExprList"}, {"left_prior": 93, "attrs": [], "is_leaf": false, "last_sibling": true, "right_prior": 95, "right_sibling": 0, "parent": 93, "left_sibling": 0, "num_children": 2, "node_number": 94, "label": "ArrayRef"}, {"left_prior": 94, "attrs": [["name", "message"]], "is_leaf": true, "last_sibling": false, "right_prior": 96, "right_sibling": 96, "parent": 94, "left_sibling": 0, "num_children": 0, "node_number": 95, "label": "ID"}, {"left_prior": 95, "attrs": [["name", "i"]], "is_leaf": true, "last_sibling": true, "right_prior": 97, "right_sibling": 0, "parent": 94, "left_sibling": 95, "num_children": 0, "node_number": 96, "label": "ID"}, {"left_prior": 96, "attrs": [], "is_leaf": false, "last_sibling": false, "right_prior": 98, "right_sibling": 171, "parent": 90, "left_sibling": 91, "num_children": 1, "node_number": 97, "label": "Compound"}, {"left_prior": 97, "attrs": [], "is_leaf": false, "last_sibling": true, "right_prior": 99, "right_sibling": 0, "parent": 97, "left_sibling": 0, "num_children": 3, "node_number": 98, "label": "If"}, {"left_prior": 98, "attrs": [], "is_leaf": false, "last_sibling": false, "right_prior": 100, "right_sibling": 105, "parent": 98, "left_sibling": 0, "num_children": 2, "node_number": 99, "label": "FuncCall"}, {"left_prior": 99, "attrs": [["name", "isupper"]], "is_leaf": true, "last_sibling": false, "right_prior": 101, "right_sibling": 101, "parent": 99, "left_sibling": 0, "num_children": 0, "node_number": 100, "label": "ID"}, {"left_prior": 100, "attrs": [], "is_leaf": false, "last_sibling": true, "right_prior": 102, "right_sibling": 0, "parent": 99, "left_sibling": 100, "num_children": 1, "node_number": 101, "label": "ExprList"}, {"left_prior": 101, "attrs": [], "is_leaf": false, "last_sibling": true, "right_prior": 103, "right_sibling": 0, "parent": 101, "left_sibling": 0, "num_children": 2, "node_number": 102, "label": "ArrayRef"}, {"left_prior": 102, "attrs": [["name", "message"]], "is_leaf": true, "last_sibling": false, "right_prior": 104, "right_sibling": 104, "parent": 102, "left_sibling": 0, "num_children": 0, "node_number": 103, "label": "ID"}, {"left_prior": 103, "attrs": [["name", "i"]], "is_leaf": true, "last_sibling": true, "right_prior": 105, "right_sibling": 0, "parent": 102, "left_sibling": 103, "num_children": 0, "node_number": 104, "label": "ID"}, {"left_prior": 104, "attrs": [], "is_leaf": false, "last_sibling": false, "right_prior": 106, "right_sibling": 138, "parent": 98, "left_sibling": 99, "num_children": 3, "node_number": 105, "label": "Compound"}, {"left_prior": 105, "attrs": [], "is_leaf": false, "last_sibling": false, "right_prior": 107, "right_sibling": 123, "parent": 105, "left_sibling": 0, "num_children": 2, "node_number": 106, "label": "FuncCall"}, {"left_prior": 106, "attrs": [["name", "printf"]], "is_leaf": true, "last_sibling": false, "right_prior": 108, "right_sibling": 108, "parent": 106, "left_sibling": 0, "num_children": 0, "node_number": 107, "label": "ID"}, {"left_prior": 107, "attrs": [], "is_leaf": false, "last_sibling": true, "right_prior": 109, "right_sibling": 0, "parent": 106, "left_sibling": 107, "num_children": 2, "node_number": 108, "label": "ExprList"}, {"left_prior": 108, "attrs": [["type", "string"], ["value", "\"%c\""]], "is_leaf": true, "last_sibling": false, "right_prior": 110, "right_sibling": 110, "parent": 108, "left_sibling": 0, "num_children": 0, "node_number": 109, "label": "Constant"}, {"left_prior": 109, "attrs": [["op", "+"]], "is_leaf": false, "last_sibling": true, "right_prior": 111, "right_sibling": 0, "parent": 108, "left_sibling": 109, "num_children": 2, "node_number": 110, "label": "BinaryOp"}, {"left_prior": 110, "attrs": [["op", "%"]], "is_leaf": false, "last_sibling": false, "right_prior": 112, "right_sibling": 122, "parent": 110, "left_sibling": 0, "num_children": 2, "node_number": 111, "label": "BinaryOp"}, {"left_prior": 111, "attrs": [["op", "-"]], "is_leaf": false, "last_sibling": false, "right_prior": 113, "right_sibling": 121, "parent": 111, "left_sibling": 0, "num_children": 2, "node_number": 112, "label": "BinaryOp"}, {"left_prior": 112, "attrs": [["op", "+"]], "is_leaf": false, "last_sibling": false, "right_prior": 114, "right_sibling": 120, "parent": 112, "left_sibling": 0, "num_children": 2, "node_number": 113, "label": "BinaryOp"}, {"left_prior": 113, "attrs": [], "is_leaf": false, "last_sibling": false, "right_prior": 115, "right_sibling": 117, "parent": 113, "left_sibling": 0, "num_children": 2, "node_number": 114, "label": "ArrayRef"}, {"left_prior": 114, "attrs": [["name", "message"]], "is_leaf": true, "last_sibling": false, "right_prior": 116, "right_sibling": 116, "parent": 114, "left_sibling": 0, "num_children": 0, "node_number": 115, "label": "ID"}, {"left_prior": 115, "attrs": [["name", "i"]], "is_leaf": true, "last_sibling": true, "right_prior": 117, "right_sibling": 0, "parent": 114, "left_sibling": 115, "num_children": 0, "node_number": 116, "label": "ID"}, {"left_prior": 116, "attrs": [], "is_leaf": false, "last_sibling": true, "right_prior": 118, "right_sibling": 0, "parent": 113, "left_sibling": 114, "num_children": 2, "node_number": 117, "label": "ArrayRef"}, {"left_prior": 117, "attrs": [["name", "key"]], "is_leaf": true, "last_sibling": false, "right_prior": 119, "right_sibling": 119, "parent": 117, "left_sibling": 0, "num_children": 0, "node_number": 118, "label": "ID"}, {"left_prior": 118, "attrs": [["name", "j"]], "is_leaf": true, "last_sibling": true, "right_prior": 120, "right_sibling": 0, "parent": 117, "left_sibling": 118, "num_children": 0, "node_number": 119, "label": "ID"}, {"left_prior": 119, "attrs": [["type", "int"], ["value", "65"]], "is_leaf": true, "last_sibling": true, "right_prior": 121, "right_sibling": 0, "parent": 112, "left_sibling": 113, "num_children": 0, "node_number": 120, "label": "Constant"}, {"left_prior": 120, "attrs": [["type", "int"], ["value", "26"]], "is_leaf": true, "last_sibling": true, "right_prior": 122, "right_sibling": 0, "parent": 111, "left_sibling": 112, "num_children": 0, "node_number": 121, "label": "Constant"}, {"left_prior": 121, "attrs": [["type", "int"], ["value", "65"]], "is_leaf": true, "last_sibling": true, "right_prior": 123, "right_sibling": 0, "parent": 110, "left_sibling": 111, "num_children": 0, "node_number": 122, "label": "Constant"}, {"left_prior": 122, "attrs": [["op", "p++"]], "is_leaf": false, "last_sibling": false, "right_prior": 124, "right_sibling": 125, "parent": 105, "left_sibling": 106, "num_children": 1, "node_number": 123, "label": "UnaryOp"}, {"left_prior": 123, "attrs": [["name", "j"]], "is_leaf": true, "last_sibling": true, "right_prior": 125, "right_sibling": 0, "parent": 123, "left_sibling": 0, "num_children": 0, "node_number": 124, "label": "ID"}, {"left_prior": 124, "attrs": [], "is_leaf": false, "last_sibling": true, "right_prior": 126, "right_sibling": 0, "parent": 105, "left_sibling": 123, "num_children": 2, "node_number": 125, "label": "If"}, {"left_prior": 125, "attrs": [["op", "=="]], "is_leaf": false, "last_sibling": false, "right_prior": 127, "right_sibling": 134, "parent": 125, "left_sibling": 0, "num_children": 2, "node_number": 126, "label": "BinaryOp"}, {"left_prior": 126, "attrs": [["name", "j"]], "is_leaf": true, "last_sibling": false, "right_prior": 128, "right_sibling": 128, "parent": 126, "left_sibling": 0, "num_children": 0, "node_number": 127, "label": "ID"}, {"left_prior": 127, "attrs": [], "is_leaf": false, "last_sibling": true, "right_prior": 129, "right_sibling": 0, "parent": 126, "left_sibling": 127, "num_children": 2, "node_number": 128, "label": "FuncCall"}, {"left_prior": 128, "attrs": [["name", "strlen"]], "is_leaf": true, "last_sibling": false, "right_prior": 130, "right_sibling": 130, "parent": 128, "left_sibling": 0, "num_children": 0, "node_number": 129, "label": "ID"}, {"left_prior": 129, "attrs": [], "is_leaf": false, "last_sibling": true, "right_prior": 131, "right_sibling": 0, "parent": 128, "left_sibling": 129, "num_children": 1, "node_number": 130, "label": "ExprList"}, {"left_prior": 130, "attrs": [], "is_leaf": false, "last_sibling": true, "right_prior": 132, "right_sibling": 0, "parent": 130, "left_sibling": 0, "num_children": 2, "node_number": 131, "label": "ArrayRef"}, {"left_prior": 131, "attrs": [["name", "argv"]], "is_leaf": true, "last_sibling": false, "right_prior": 133, "right_sibling": 133, "parent": 131, "left_sibling": 0, "num_children": 0, "node_number": 132, "label": "ID"}, {"left_prior": 132, "attrs": [["type", "int"], ["value", "1"]], "is_leaf": true, "last_sibling": true, "right_prior": 134, "right_sibling": 0, "parent": 131, "left_sibling": 132, "num_children": 0, "node_number": 133, "label": "Constant"}, {"left_prior": 133, "attrs": [], "is_leaf": false, "last_sibling": true, "right_prior": 135, "right_sibling": 0, "parent": 125, "left_sibling": 126, "num_children": 1, "node_number": 134, "label": "Compound"}, {"left_prior": 134, "attrs": [["op", "="]], "is_leaf": false, "last_sibling": true, "right_prior": 136, "right_sibling": 0, "parent": 134, "left_sibling": 0, "num_children": 2, "node_number": 135, "label": "Assignment"}, {"left_prior": 135, "attrs": [["name", "j"]], "is_leaf": true, "last_sibling": false, "right_prior": 137, "right_sibling": 137, "parent": 135, "left_sibling": 0, "num_children": 0, "node_number": 136, "label": "ID"}, {"left_prior": 136, "attrs": [["type", "int"], ["value", "0"]], "is_leaf": true, "last_sibling": true, "right_prior": 138, "right_sibling": 0, "parent": 135, "left_sibling": 136, "num_children": 0, "node_number": 137, "label": "Constant"}, {"left_prior": 137, "attrs": [], "is_leaf": false, "last_sibling": true, "right_prior": 139, "right_sibling": 0, "parent": 98, "left_sibling": 105, "num_children": 3, "node_number": 138, "label": "Compound"}, {"left_prior": 138, "attrs": [], "is_leaf": false, "last_sibling": false, "right_prior": 140, "right_sibling": 156, "parent": 138, "left_sibling": 0, "num_children": 2, "node_number": 139, "label": "FuncCall"}, {"left_prior": 139, "attrs": [["name", "printf"]], "is_leaf": true, "last_sibling": false, "right_prior": 141, "right_sibling": 141, "parent": 139, "left_sibling": 0, "num_children": 0, "node_number": 140, "label": "ID"}, {"left_prior": 140, "attrs": [], "is_leaf": false, "last_sibling": true, "right_prior": 142, "right_sibling": 0, "parent": 139, "left_sibling": 140, "num_children": 2, "node_number": 141, "label": "ExprList"}, {"left_prior": 141, "attrs": [["type", "string"], ["value", "\"%c\""]], "is_leaf": true, "last_sibling": false, "right_prior": 143, "right_sibling": 143, "parent": 141, "left_sibling": 0, "num_children": 0, "node_number": 142, "label": "Constant"}, {"left_prior": 142, "attrs": [["op", "+"]], "is_leaf": false, "last_sibling": true, "right_prior": 144, "right_sibling": 0, "parent": 141, "left_sibling": 142, "num_children": 2, "node_number": 143, "label": "BinaryOp"}, {"left_prior": 143, "attrs": [["op", "%"]], "is_leaf": false, "last_sibling": false, "right_prior": 145, "right_sibling": 155, "parent": 143, "left_sibling": 0, "num_children": 2, "node_number": 144, "label": "BinaryOp"}, {"left_prior": 144, "attrs": [["op", "-"]], "is_leaf": false, "last_sibling": false, "right_prior": 146, "right_sibling": 154, "parent": 144, "left_sibling": 0, "num_children": 2, "node_number": 145, "label": "BinaryOp"}, {"left_prior": 145, "attrs": [["op", "+"]], "is_leaf": false, "last_sibling": false, "right_prior": 147, "right_sibling": 153, "parent": 145, "left_sibling": 0, "num_children": 2, "node_number": 146, "label": "BinaryOp"}, {"left_prior": 146, "attrs": [], "is_leaf": false, "last_sibling": false, "right_prior": 148, "right_sibling": 150, "parent": 146, "left_sibling": 0, "num_children": 2, "node_number": 147, "label": "ArrayRef"}, {"left_prior": 147, "attrs": [["name", "message"]], "is_leaf": true, "last_sibling": false, "right_prior": 149, "right_sibling": 149, "parent": 147, "left_sibling": 0, "num_children": 0, "node_number": 148, "label": "ID"}, {"left_prior": 148, "attrs": [["name", "i"]], "is_leaf": true, "last_sibling": true, "right_prior": 150, "right_sibling": 0, "parent": 147, "left_sibling": 148, "num_children": 0, "node_number": 149, "label": "ID"}, {"left_prior": 149, "attrs": [], "is_leaf": false, "last_sibling": true, "right_prior": 151, "right_sibling": 0, "parent": 146, "left_sibling": 147, "num_children": 2, "node_number": 150, "label": "ArrayRef"}, {"left_prior": 150, "attrs": [["name", "key"]], "is_leaf": true, "last_sibling": false, "right_prior": 152, "right_sibling": 152, "parent": 150, "left_sibling": 0, "num_children": 0, "node_number": 151, "label": "ID"}, {"left_prior": 151, "attrs": [["name", "j"]], "is_leaf": true, "last_sibling": true, "right_prior": 153, "right_sibling": 0, "parent": 150, "left_sibling": 151, "num_children": 0, "node_number": 152, "label": "ID"}, {"left_prior": 152, "attrs": [["type", "int"], ["value", "97"]], "is_leaf": true, "last_sibling": true, "right_prior": 154, "right_sibling": 0, "parent": 145, "left_sibling": 146, "num_children": 0, "node_number": 153, "label": "Constant"}, {"left_prior": 153, "attrs": [["type", "int"], ["value", "26"]], "is_leaf": true, "last_sibling": true, "right_prior": 155, "right_sibling": 0, "parent": 144, "left_sibling": 145, "num_children": 0, "node_number": 154, "label": "Constant"}, {"left_prior": 154, "attrs": [["type", "int"], ["value", "97"]], "is_leaf": true, "last_sibling": true, "right_prior": 156, "right_sibling": 0, "parent": 143, "left_sibling": 144, "num_children": 0, "node_number": 155, "label": "Constant"}, {"left_prior": 155, "attrs": [["op", "p++"]], "is_leaf": false, "last_sibling": false, "right_prior": 157, "right_sibling": 158, "parent": 138, "left_sibling": 139, "num_children": 1, "node_number": 156, "label": "UnaryOp"}, {"left_prior": 156, "attrs": [["name", "j"]], "is_leaf": true, "last_sibling": true, "right_prior": 158, "right_sibling": 0, "parent": 156, "left_sibling": 0, "num_children": 0, "node_number": 157, "label": "ID"}, {"left_prior": 157, "attrs": [], "is_leaf": false, "last_sibling": true, "right_prior": 159, "right_sibling": 0, "parent": 138, "left_sibling": 156, "num_children": 2, "node_number": 158, "label": "If"}, {"left_prior": 158, "attrs": [["op", "=="]], "is_leaf": false, "last_sibling": false, "right_prior": 160, "right_sibling": 167, "parent": 158, "left_sibling": 0, "num_children": 2, "node_number": 159, "label": "BinaryOp"}, {"left_prior": 159, "attrs": [["name", "j"]], "is_leaf": true, "last_sibling": false, "right_prior": 161, "right_sibling": 161, "parent": 159, "left_sibling": 0, "num_children": 0, "node_number": 160, "label": "ID"}, {"left_prior": 160, "attrs": [], "is_leaf": false, "last_sibling": true, "right_prior": 162, "right_sibling": 0, "parent": 159, "left_sibling": 160, "num_children": 2, "node_number": 161, "label": "FuncCall"}, {"left_prior": 161, "attrs": [["name", "strlen"]], "is_leaf": true, "last_sibling": false, "right_prior": 163, "right_sibling": 163, "parent": 161, "left_sibling": 0, "num_children": 0, "node_number": 162, "label": "ID"}, {"left_prior": 162, "attrs": [], "is_leaf": false, "last_sibling": true, "right_prior": 164, "right_sibling": 0, "parent": 161, "left_sibling": 162, "num_children": 1, "node_number": 163, "label": "ExprList"}, {"left_prior": 163, "attrs": [], "is_leaf": false, "last_sibling": true, "right_prior": 165, "right_sibling": 0, "parent": 163, "left_sibling": 0, "num_children": 2, "node_number": 164, "label": "ArrayRef"}, {"left_prior": 164, "attrs": [["name", "argv"]], "is_leaf": true, "last_sibling": false, "right_prior": 166, "right_sibling": 166, "parent": 164, "left_sibling": 0, "num_children": 0, "node_number": 165, "label": "ID"}, {"left_prior": 165, "attrs": [["type", "int"], ["value", "1"]], "is_leaf": true, "last_sibling": true, "right_prior": 167, "right_sibling": 0, "parent": 164, "left_sibling": 165, "num_children": 0, "node_number": 166, "label": "Constant"}, {"left_prior": 166, "attrs": [], "is_leaf": false, "last_sibling": true, "right_prior": 168, "right_sibling": 0, "parent": 158, "left_sibling": 159, "num_children": 1, "node_number": 167, "label": "Compound"}, {"left_prior": 167, "attrs": [["op", "="]], "is_leaf": false, "last_sibling": true, "right_prior": 169, "right_sibling": 0, "parent": 167, "left_sibling": 0, "num_children": 2, "node_number": 168, "label": "Assignment"}, {"left_prior": 168, "attrs": [["name", "j"]], "is_leaf": true, "last_sibling": false, "right_prior": 170, "right_sibling": 170, "parent": 168, "left_sibling": 0, "num_children": 0, "node_number": 169, "label": "ID"}, {"left_prior": 169, "attrs": [["type", "int"], ["value", "0"]], "is_leaf": true, "last_sibling": true, "right_prior": 171, "right_sibling": 0, "parent": 168, "left_sibling": 169, "num_children": 0, "node_number": 170, "label": "Constant"}, {"left_prior": 170, "attrs": [], "is_leaf": false, "last_sibling": true, "right_prior": 172, "right_sibling": 0, "parent": 90, "left_sibling": 97, "num_children": 1, "node_number": 171, "label": "Compound"}, {"left_prior": 171, "attrs": [], "is_leaf": false, "last_sibling": true, "right_prior": 173, "right_sibling": 0, "parent": 171, "left_sibling": 0, "num_children": 2, "node_number": 172, "label": "FuncCall"}, {"left_prior": 172, "attrs": [["name", "printf"]], "is_leaf": true, "last_sibling": false, "right_prior": 174, "right_sibling": 174, "parent": 172, "left_sibling": 0, "num_children": 0, "node_number": 173, "label": "ID"}, {"left_prior": 173, "attrs": [], "is_leaf": false, "last_sibling": true, "right_prior": 175, "right_sibling": 0, "parent": 172, "left_sibling": 173, "num_children": 2, "node_number": 174, "label": "ExprList"}, {"left_prior": 174, "attrs": [["type", "string"], ["value", "\"%c\""]], "is_leaf": true, "last_sibling": false, "right_prior": 176, "right_sibling": 176, "parent": 174, "left_sibling": 0, "num_children": 0, "node_number": 175, "label": "Constant"}, {"left_prior": 175, "attrs": [], "is_leaf": false, "last_sibling": true, "right_prior": 177, "right_sibling": 0, "parent": 174, "left_sibling": 175, "num_children": 2, "node_number": 176, "label": "ArrayRef"}, {"left_prior": 176, "attrs": [["name", "message"]], "is_leaf": true, "last_sibling": false, "right_prior": 178, "right_sibling": 178, "parent": 176, "left_sibling": 0, "num_children": 0, "node_number": 177, "label": "ID"}, {"left_prior": 177, "attrs": [["name", "i"]], "is_leaf": true, "last_sibling": true, "right_prior": 179, "right_sibling": 0, "parent": 176, "left_sibling": 177, "num_children": 0, "node_number": 178, "label": "ID"}, {"left_prior": 178, "attrs": [], "is_leaf": false, "last_sibling": true, "right_prior": 180, "right_sibling": 0, "parent": 82, "left_sibling": 83, "num_children": 2, "node_number": 179, "label": "FuncCall"}, {"left_prior": 179, "attrs": [["name", "printf"]], "is_leaf": true, "last_sibling": false, "right_prior": 181, "right_sibling": 181, "parent": 179, "left_sibling": 0, "num_children": 0, "node_number": 180, "label": "ID"}, {"left_prior": 180, "attrs": [], "is_leaf": false, "last_sibling": true, "right_prior": 182, "right_sibling": 0, "parent": 179, "left_sibling": 180, "num_children": 1, "node_number": 181, "label": "ExprList"}, {"left_prior": 181, "attrs": [["type", "string"], ["value", "\"\\n\""]], "is_leaf": true, "last_sibling": true, "right_prior": 183, "right_sibling": 0, "parent": 181, "left_sibling": 0, "num_children": 0, "node_number": 182, "label": "Constant"}, {"left_prior": 182, "attrs": [], "is_leaf": false, "last_sibling": true, "right_prior": 184, "right_sibling": 0, "parent": 2, "left_sibling": 78, "num_children": 1, "node_number": 183, "label": "Return"}, {"left_prior": 183, "attrs": [["type", "int"], ["value", "0"]], "is_leaf": true, "last_sibling": true, "right_prior": 0, "right_sibling": 0, "parent": 183, "left_sibling": 0, "num_children": 0, "node_number": 184, "label": "Constant"}]
